{
    "2024": [
        {
            "question": "Which of the following is/are (a) component/s of effective verbal communication?",
            "options": ["Active listening", "Filler words", "Computer jargon", "Interruption", "Complex vocabulary"],
            "correctAnswers": [0],
            "explanation": "Active listening is a critical component of effective communication, ensuring the listener understands the message fully."
        },
        {
            "question": "Which of the following is NOT a categorization(s) of plagiarism?",
            "options": ["Idea plagiarism", "Code plagiarism", "Improper use of quotation marks", "Exam plagiarism", "Misinformation of references"],
            "correctAnswers": [2],
            "explanation": "While improper use of quotation marks can lead to plagiarism, it is often considered a citation error rather than a standalone category of plagiarism like 'Idea' or 'Code' plagiarism."
        }
    ],
    "2023": [],
    "2022": []
}